[
  {
    "id": 1,
    "userId": "user123",
    "category": "Groceries",
    "amount": 350,
    "date": "01-08-2025",
    "description": "Vegetables and fruits",
    "isRecurring": true,
    "recurrence": "weekly"
  },
  {
    "id": 2,
    "userId": "user123",
    "category": "Transport",
    "amount": 120,
    "date": "02-09-2025",
    "description": "Uber to office",
    "isRecurring": false,
    "recurrence": "off"
  },
  {
    "id": 3,
    "userId": "user456",
    "category": "Entertainment",
    "amount": 499,
    "date": "03-08-2025",
    "description": "Netflix subscription",
    "isRecurring": true,
    "recurrence": "monthly"
  },
  {
    "id": 4,
    "userId": "user123",
    "category": "Utilities",
    "amount": 850,
    "date": "05-07-2025",
    "description": "Electricity bill",
    "isRecurring": true,
    "recurrence": "monthly"
  },
  {
    "id": 5,
    "userId": "user789",
    "category": "Rent",
    "amount": 12500,
    "date": "01-07-2025",
    "description": "Monthly rent",
    "isRecurring": true,
    "recurrence": "monthly"
  },
  {
    "id": 6,
    "userId": "user456",
    "category": "Dining Out",
    "amount": 640,
    "date": "07-09-2025",
    "description": "Dinner with friends",
    "isRecurring": false,
    "recurrence": "0ff"
  },
  {
    "id": 7,
    "userId": "user123",
    "category": "Groceries",
    "amount": 410,
    "date": "10-08-2025",
    "description": "Weekend grocery run",
    "isRecurring": true,
    "recurrence": "weekly"
  },
  {
    "id": 8,
    "userId": "user456",
    "category": "Subscriptions",
    "amount": 299,
    "date": "11-08-2025",
    "description": "Spotify Premium",
    "isRecurring": true,
    "recurrence": "monthly"
  },
  {
    "id": 9,
    "userId": "user123",
    "category": "Healthcare",
    "amount": 1500,
    "date": "15-09-2025",
    "description": "Doctor visit",
    "isRecurring": false,
    "recurrence": "0ff"
  },
  {
    "id": 10,
    "userId": "user789",
    "category": "Transport",
    "amount": 90,
    "date": "17-08-2025",
    "description": "Bus pass",
    "isRecurring": true,
    "recurrence": "monthly"
  },
  {
    "id": 11,
    "userId": "user123",
    "category": "Shopping",
    "amount": 2200,
    "date": "19-07-2025",
    "description": "New shoes",
    "isRecurring": false,
    "recurrence": "0ff"
  },
  {
    "id": 12,
    "userId": "user456",
    "category": "Utilities",
    "amount": 750,
    "date": "20-08-2025",
    "description": "Water bill",
    "isRecurring": true,
    "recurrence": "monthly"
  },
  {
    "id": 13,
    "userId": "user789",
    "category": "Dining Out",
    "amount": 980,
    "date": "21-09-2025",
    "description": "Family dinner",
    "isRecurring": false,
    "recurrence": "0ff"
  },
  {
    "id": 14,
    "userId": "user123",
    "category": "Entertainment",
    "amount": 120,
    "date": "22-08-2025",
    "description": "Movie ticket",
    "isRecurring": false,
    "recurrence": "0ff"
  },
  {
    "id": 15,
    "userId": "user456",
    "category": "Groceries",
    "amount": 370,
    "date": "25-07-2025",
    "description": "Weekend supplies",
    "isRecurring": true,
    "recurrence": "weekly"
  },
  {
    "id": 16,
    "userId": "user789",
    "category": "Transport",
    "amount": 250,
    "date": "26-09-2025",
    "description": "Cab rides",
    "isRecurring": false,
    "recurrence": "off"
  },
  {
    "id": 17,
    "userId": "user123",
    "category": "Rent",
    "amount": 12000,
    "date": "01-08-2025",
    "description": "Shop rent",
    "isRecurring": true,
    "recurrence": "monthly"
  },
  {
    "id": 18,
    "userId": "user456",
    "category": "Entertainment",
    "amount": 399,
    "date": "02-07-2025",
    "description": "Book purchase",
    "isRecurring": false,
    "recurrence": "0ff"
  },
  {
    "id": 19,
    "userId": "user789",
    "category": "Healthcare",
    "amount": 2300,
    "date": "04-09-2025",
    "description": "Lab tests",
    "isRecurring": true,
    "recurrence": "monthly"
  },
  {
    "id": 20,
    "userId": "user123",
    "category": "Subscriptions",
    "amount": 199,
    "date": "05-09-2025",
    "description": "Amazon Prime",
    "isRecurring": true,
    "recurrence": "yearly"
  },
    {
        "id": 21,
        "userId": "user456",
        "category": "Shopping",
        "amount": 1500,
        "date": "06-09-2025",
        "description": "Clothes shopping",
        "isRecurring": false,
        "recurrence": "0ff"
    }
]